{
  "project_info": {
    "project_number": "658357887443",
    "project_id": "telematics-641f1",
    "storage_bucket": "telematics-641f1.appspot.com"
  },
  "client": [
    {
      "client_info": {
        "mobilesdk_app_id": "1:658357887443:android:abcdef1234567890",
        "android_client_info": {
          "package_name": "com.example.pervendur25"
        }
      },
      "oauth_client": [],
      "api_key": [
        {
          "current_key": "AIzaSyB8d9FirFkz3fyBn7m4WOCWP7vh834nXrQ"
        }
      ],
      "services": {
        "appinvite_service": {
          "other_platform_oauth_client": []
        }
      }
    }
  ],
  "configuration_version": "1"
}